QtSplashScreen/SplashScreen.py
QtSplashScreen/__init__.py
QtSplashScreen/__main__.py
QtSplashScreen-5.15.2.dist-info/METADATA
QtSplashScreen-5.15.2.dist-info/WHEEL
QtSplashScreen-5.15.2.dist-info/entry_points.txt
QtSplashScreen-5.15.2.dist-info/top_level.txt
QtSplashScreen-5.15.2.dist-info/RECORD
