Metadata-Version: 2.1
Name: QtSplashScreen
Version: 5.15.2
Summary: A PyQt5 Splash Screen Demo and Template
Home-page: UNKNOWN
Author: Pranav
License: MIT
Keywords: QtSplashScreen,SplashScreen
Platform: UNKNOWN
Classifier: Programming Language :: Python
Classifier: Programming Language :: Python :: 3.9
Classifier: License :: OSI Approved :: MIT License
Requires-Python: >=3.8
Requires-Dist: PyQt5 (==5.15.2)
Requires-Dist: pip (>=21.0.1)
Requires-Dist: wheel
Requires-Dist: setuptools (>=49.0.0)
